[{"name":"button","x":0,"y":0,"w":0,"h":0},[{"name":"sBlock","x":0,"y":0,"w":0,"h":0},{"name":"sBlock","x":0,"y":0,"w":0,"h":0},{"name":"sBlock","x":0,"y":0,"w":0,"h":0},{"name":"sBlock","x":0,"y":0,"w":0,"h":0},{"name":"sBlock","x":0,"y":0,"w":0,"h":0},{"name":"sBlock","x":0,"y":0,"w":0,"h":0},{"name":"sBlock","x":0,"y":0,"w":0,"h":0},{"name":"sBlock","x":0,"y":0,"w":0,"h":0},{"name":"sBlock","x":0,"y":0,"w":0,"h":0},{"name":"sBlock","x":0,"y":0,"w":0,"h":0},{"name":"sBlock","x":0,"y":0,"w":0,"h":0},{"name":"sBlock","x":0,"y":0,"w":0,"h":0},{"name":"sBlock","x":0,"y":0,"w":0,"h":0},{"name":"sBlock","x":0,"y":0,"w":0,"h":0},{"name":"sBlock","x":0,"y":0,"w":0,"h":0},{"name":"sBlock","x":0,"y":0,"w":0,"h":0},{"name":"sBlock","x":0,"y":0,"w":0,"h":0},{"name":"sBlock","x":0,"y":0,"w":0,"h":0},{"name":"sBlock","x":0,"y":0,"w":0,"h":0}],[{"name":"sEnemyFly","x":0,"y":0,"w":0,"h":0},{"name":"sEnemyFly","x":0,"y":0,"w":0,"h":0}],[{"name":"sEnemyWalk","x":0,"y":0,"w":0,"h":0},{"name":"sEnemyWalk","x":0,"y":0,"w":0,"h":0},{"name":"sEnemyWalk","x":0,"y":0,"w":0,"h":0},{"name":"sEnemyWalk","x":0,"y":0,"w":0,"h":0}],[{"name":"sExplode","x":0,"y":0,"w":0,"h":0},{"name":"sExplode","x":0,"y":0,"w":0,"h":0},{"name":"sExplode","x":0,"y":0,"w":0,"h":0},{"name":"sExplode","x":0,"y":0,"w":0,"h":0},{"name":"sExplode","x":0,"y":0,"w":0,"h":0},{"name":"sExplode","x":0,"y":0,"w":0,"h":0},{"name":"sExplode","x":0,"y":0,"w":0,"h":0}],[{"name":"sPlayerFly","x":0,"y":0,"w":0,"h":0},{"name":"sPlayerFly","x":0,"y":0,"w":0,"h":0}],[{"name":"sPlayerWalk","x":0,"y":0,"w":0,"h":0},{"name":"sPlayerWalk","x":0,"y":0,"w":0,"h":0},{"name":"sPlayerWalk","x":0,"y":0,"w":0,"h":0},{"name":"sPlayerWalk","x":0,"y":0,"w":0,"h":0}],[{"name":"sPop","x":0,"y":0,"w":0,"h":0},{"name":"sPop","x":0,"y":0,"w":0,"h":0},{"name":"sPop","x":0,"y":0,"w":0,"h":0},{"name":"sPop","x":0,"y":0,"w":0,"h":0},{"name":"sPop","x":0,"y":0,"w":0,"h":0},{"name":"sPop","x":0,"y":0,"w":0,"h":0}],[{"name":"sSpawn","x":0,"y":0,"w":0,"h":0},{"name":"sSpawn","x":0,"y":0,"w":0,"h":0},{"name":"sSpawn","x":0,"y":0,"w":0,"h":0},{"name":"sSpawn","x":0,"y":0,"w":0,"h":0}]]