[
  {
    "name": "billboard",
    "width": 48,
    "height": 48,
    "images": [
      {
        "x": 0,
        "y": 0
      }
    ]
  },
  {
    "name": "tree",
    "width": 32,
    "height": 48,
    "images": [
      {
        "x": 60,
        "y": 0
      },
      {
        "x": 100,
        "y": 0
      },
      {
        "x": 140,
        "y": 0
      }
    ]
  },
  {
    "name": "effect",
    "width": 40,
    "height": 28,
    "images": [
      {
        "x": 0,
        "y": 50
      },
      {
        "x": 40,
        "y": 50
      },
      {
        "x": 80,
        "y": 50
      }
    ]
  },
  {
    "name": "walkDown",
    "width": 16,
    "height": 24,
    "images": [
      {
        "x": 120,
        "y": 50
      },
      {
        "x": 140,
        "y": 50
      },
      {
        "x": 160,
        "y": 50
      },
      {
        "x": 180,
        "y": 50
      },
      {
        "x": 0,
        "y": 80
      },
      {
        "x": 20,
        "y": 80
      },
      {
        "x": 40,
        "y": 80
      },
      {
        "x": 60,
        "y": 80
      }
    ]
  },
  {
    "name": "tiles",
    "width": 16,
    "height": 16,
    "images": [
      {
        "x": 80,
        "y": 80
      },
      {
        "x": 100,
        "y": 80
      }
    ]
  },
  {
    "name": "particle",
    "width": 8,
    "height": 8,
    "images": [
      {
        "x": 120,
        "y": 80
      },
      {
        "x": 140,
        "y": 80
      },
      {
        "x": 160,
        "y": 80
      },
      {
        "x": 180,
        "y": 80
      },
      {
        "x": 120,
        "y": 90
      },
      {
        "x": 140,
        "y": 90
      },
      {
        "x": 160,
        "y": 90
      },
      {
        "x": 180,
        "y": 90
      }
    ]
  }
]